{
    "title": "Kth smallest/largest element in an array",
    "link_to_project": "https://www.geeksforgeeks.org/kth-smallestlargest-element-unsorted-array/",
    "language": "python",
    "tags": [
        "kth element",
        "sorting",
        "heap",
        "data structures"
    ],
    "path": "python/algorithms/other/k_stat/main.py",
    "contributors": [
        {
            "name": "Pavel",
            "last_name": "Eroshkin",
            "email": "eroshkin321@gmail.com"
        }
    ]
}